LICENSE
MANIFEST.in
README.md
setup.py
bin/tdm_gfs_fetch
bin/tdm_grib2cf
bin/tdm_link_grib
bin/tdm_map_to_lonlat
bin/tdm_map_to_tree
bin/tdm_radar_events
bin/tdm_radar_nc_to_geo
bin/tdm_rainfall
bin/tdm_wrf_configurator
tdm/__init__.py
tdm/version.py
tdm.egg-info/PKG-INFO
tdm.egg-info/SOURCES.txt
tdm.egg-info/dependency_links.txt
tdm.egg-info/top_level.txt
tdm/gfs/__init__.py
tdm/gfs/noaa/__init__.py
tdm/gfs/noaa/noaa_fetcher.py
tdm/radar/__init__.py
tdm/radar/utils.py
tdm/wrf/__init__.py
tdm/wrf/configuration_checker.py
tdm/wrf/configurator.py
tdm/wrf/constants.py
tdm/wrf/projector.py
tdm/wrf/summarizer.py
test/all_tests.py
test/test_top_level.py
test/gfs/__init__.py
test/gfs/test_noaa_fetcher.py
test/radar/__init__.py
test/radar/test_utils.py
test/wrf/__init__.py
test/wrf/minimal.yaml
test/wrf/test_configurator.py